arcverse/__init__.py
arcverse/__main__.py
arcverse/grid.py
arcverse/utils.py
arcverse-0.0.1a2.dist-info/LICENSE
arcverse-0.0.1a2.dist-info/METADATA
arcverse-0.0.1a2.dist-info/WHEEL
arcverse-0.0.1a2.dist-info/RECORD
