Metadata-Version: 2.3
Name: arcverse
Version: 0.0.1a2
Summary: arcverse is a library for creating synthesizing arc-agi like datasets with knobs to control different degrees of freedom.
License: MIT
Author: Abhay Kashyap
Requires-Python: >=3.10.1,<=3.13.1
Classifier: Development Status :: 2 - Pre-Alpha
Classifier: Intended Audience :: Developers
Classifier: License :: OSI Approved :: MIT License
Classifier: Natural Language :: English
Classifier: Programming Language :: Python :: 3
Classifier: Programming Language :: Python :: 3.11
Classifier: Programming Language :: Python :: 3.12
Classifier: Programming Language :: Python :: 3.13
Requires-Dist: click (>=8.1.8,<9.0.0)
Requires-Dist: loguru (>=0.7.3,<0.8.0)
Requires-Dist: numpy (>=2.2.3,<3.0.0)
Requires-Dist: pillow (>=11.1.0,<12.0.0)
Requires-Dist: scipy (>=1.15.2,<2.0.0)
Project-URL: Changelog, https://github.com/hayabhay/arcverse/releases
Project-URL: Documentation, https://hayabhay.github.io/arcverse
Project-URL: Homepage, https://hayabhay.github.io/arcverse
Project-URL: Repository, https://github.com/hayabhay/arcverse
